{
  "project_info": {
    "project_number": "437517992099",
    "project_id": "lic-policy-c0d0b",
    "storage_bucket": "lic-policy-c0d0b.firebasestorage.app"
  },
  "client": [
    {
      "client_info": {
        "mobilesdk_app_id": "1:437517992099:android:7558acef7af36248b3ff16",
        "android_client_info": {
          "package_name": "com.example.licpolicyhelper"
        }
      },
      "oauth_client": [],
      "api_key": [
        {
          "current_key": "AIzaSyBWZr_hasJCdf03yZa7biIWXMuISNVwZgc"
        }
      ],
      "services": {
        "appinvite_service": {
          "other_platform_oauth_client": []
        }
      }
    }
  ],
  "configuration_version": "1"
}